yacker/__init__.py
yacker/__main__.py
yacker/yacker.py
matildapeak_yacker-2019.1.dist-info/LICENCE.txt
matildapeak_yacker-2019.1.dist-info/METADATA
matildapeak_yacker-2019.1.dist-info/WHEEL
matildapeak_yacker-2019.1.dist-info/entry_points.txt
matildapeak_yacker-2019.1.dist-info/top_level.txt
matildapeak_yacker-2019.1.dist-info/RECORD
