Metadata-Version: 2.1
Name: matildapeak-yacker
Version: 2019.1
Summary: A YAML packer-wrapper tool
Home-page: https://gitlab.com/matilda.peak/yacker
Author: Alan Christie
Author-email: alan.christie@matildapeak.com
License: MIT
Keywords: configuration
Platform: any
Classifier: Development Status :: 5 - Production/Stable
Classifier: Environment :: Console
Classifier: Intended Audience :: Developers
Classifier: License :: OSI Approved :: MIT License
Classifier: Programming Language :: Python :: 2.7
Classifier: Programming Language :: Python :: 3.6
Classifier: Programming Language :: Python :: 3.7
Classifier: Topic :: System :: Installation/Setup
Classifier: Operating System :: POSIX :: Linux
Requires-Dist: PyYAML (==3.13)
